ine_exercises_tools/__init__.py
ine_exercises_tools/__main__.py
ine_exercises_tools/authenticator.py
ine_exercises_tools/models.py
ine_exercises_tools/strategies.py
ine_exercises_tools-0.0.7.dist-info/WHEEL
ine_exercises_tools-0.0.7.dist-info/METADATA
ine_exercises_tools-0.0.7.dist-info/RECORD
