Metadata-Version: 2.1
Name: ine-exercises-tools
Version: 0.0.7
Summary: 
Author: Santiago Basulto
Author-email: santiago.basulto@gmail.com
Requires-Python: >=3.8,<4.0
Classifier: Programming Language :: Python :: 3
Classifier: Programming Language :: Python :: 3.8
Requires-Dist: PyGithub (>=1.51,<2.0)
Requires-Dist: click (>=7.1.2,<8.0.0)
Requires-Dist: colorful (>=0.5.4,<0.6.0)
Requires-Dist: requests-toolbelt (>=0.9.1,<0.10.0)
